oi_voice/__init__.py
oi_voice/cli.py
oi_voice/speech_to_text.py
oi_voice/text_to_speech.py
oi_voice-0.1.0.dist-info/METADATA
oi_voice-0.1.0.dist-info/WHEEL
oi_voice-0.1.0.dist-info/entry_points.txt
oi_voice-0.1.0.dist-info/top_level.txt
oi_voice-0.1.0.dist-info/RECORD
