Metadata-Version: 2.1
Name: oi-voice
Version: 0.1.0
Classifier: Programming Language :: Python :: 3
Classifier: License :: OSI Approved :: MIT License
Classifier: Operating System :: OS Independent
Requires-Python: >=3.6
Requires-Dist: faster-whisper
Requires-Dist: open-interpreter
Requires-Dist: click
Requires-Dist: requests
Requires-Dist: pyaudio
Requires-Dist: pydub
